{"cameraMode":{"drawMode":0,"name":"Shaded","section":"Shading Mode"},"sceneLighting":false,"audioPlay":false,"sceneViewState":{"m_AlwaysRefresh":false,"showFog":true,"showSkybox":false,"showFlares":true,"showImageEffects":true,"showParticleSystems":true,"showVisualEffectGraphs":true,"m_FxEnabled":true},"in2DMode":false,"pivot":{"x":1.7659826278686524,"y":2.1818130016326906,"z":5.109244346618652},"rotation":{"x":0.004789402708411217,"y":-0.9330906867980957,"z":0.35956162214279177,"w":0.012410434894263745},"size":1.9165318012237549,"orthographic":false}